<?xml version="1.0" encoding="UTF-8"?>
<objects serializationModel="Studio.01.09.00">
    <object class="AudioFile" id="{2b828eb8-387e-4701-87e7-c6347178029a}">
        <property name="assetPath">
            <value>Musiques/Sad 128 bpm.wav</value>
        </property>
        <property name="isStreaming">
            <value>true</value>
        </property>
        <property name="frequencyInKHz">
            <value>44.0999985</value>
        </property>
        <property name="channelCount">
            <value>2</value>
        </property>
        <property name="length">
            <value>112.5195238095238</value>
        </property>
        <relationship name="masterAssetFolder">
            <destination>{120238d6-3397-4bbb-967d-18dac9259100}</destination>
        </relationship>
    </object>
</objects>
